aws_sherlock/__init__.py
aws_sherlock/__main__.py
aws_sherlock/logs_client.py
aws_sherlock-0.1.4.dist-info/LICENSE
aws_sherlock-0.1.4.dist-info/METADATA
aws_sherlock-0.1.4.dist-info/WHEEL
aws_sherlock-0.1.4.dist-info/entry_points.txt
aws_sherlock-0.1.4.dist-info/RECORD
