Metadata-Version: 2.3
Name: aws-sherlock
Version: 0.1.4
Summary: CLI tool for extracting AWS CloudWatch Logs locally.
License: MIT License
Keywords: aws,cloudwatch,logs,cli,analysis
Author: Eric Villa
Author-email: eric.villa91@gmail.com
Requires-Python: >=3.13
Classifier: License :: OSI Approved :: MIT License
Classifier: Programming Language :: Python
Classifier: Programming Language :: Python :: 3
Requires-Dist: boto3 (>=1.40.27,<2.0.0)
Requires-Dist: click (>=8.2.1,<9.0.0)
Project-URL: Homepage, https://github.com/ericvilla/aws-sherlock
Project-URL: Issues, https://github.com/ericvilla/aws-sherlock/issues
Project-URL: Repository, https://github.com/ericvilla/aws-sherlock
